{"ModuleCode": "EC4303", "Types": ["Module"], "History": [{"ExamDate": "2017-11-27T09:00+0800", "Timetable": [{"LessonType": "Seminar-Style Module Class", "WeekText": "Every Week", "DayText": "Wednesday", "Venue": "AS1-0301", "ClassNo": "1", "EndTime": "1500", "StartTime": "1200"}], "Semester": 1, "LecturePeriods": ["Wednesday Afternoon"]}], "Workload": "2-1-0-2-7.5", "ModuleTitle": "Econometrics III", "Prerequisite": "Cohort 2011 and before: Completed 80 MCs, including 28 MCs in EC, with a minimum CAP of 3.50 or be on the Honours track. EC3101, EC3102, and EC3304. Cohort 2012 onwards: Completed 80 MCs, including 28 MCs in EC, with a minimum CAP of 3.20 or be on the Honours track. EC3101, EC3102, EC3304", "LockedModules": [], "AcadYear": "2017/2018", "ModuleDescription": "This module is aimed at consolidating what was covered in Econometrics I and II and provide a reasonable training in econometric theory and sound empirical analyses. In addition the module will cover non-linear models, time series econometrics (including cointegration and error correction models), simultaneous equations models and more on other topics such as microeconometrics. The module will be highly useful for honours theses that deal with applied problems.", "Department": "Economics", "CorsBiddingStats": [{"AcadYear": "2010/2011", "Quota": "10", "Faculty": "Arts & Social Sciences", "HighestBid": "1101", "LowestSuccessfulBid": "1", "LowestBid": "2", "Semester": "2", "Round": "1A", "Bidders": "7", "StudentAcctType": "Returning Students [P]", "Group": "Seminar-Style Module Class 1"}, {"AcadYear": "2010/2011", "Quota": "3", "Faculty": "Arts & Social Sciences", "HighestBid": "900", "LowestSuccessfulBid": "1", "LowestBid": "900", "Semester": "2", "Round": "1B", "Bidders": "1", "StudentAcctType": "Returning Students [P]", "Group": "Seminar-Style Module Class 1"}, {"AcadYear": "2010/2011", "Quota": "2", "Faculty": "Arts & Social Sciences", "HighestBid": "1", "LowestSuccessfulBid": "1", "LowestBid": "1", "Semester": "2", "Round": "2A", "Bidders": "1", "StudentAcctType": "Returning Students and New Students [P]", "Group": "Seminar-Style Module Class 1"}, {"AcadYear": "2010/2011", "Quota": "3", "Faculty": "Arts & Social Sciences", "HighestBid": "1", "LowestSuccessfulBid": "1", "LowestBid": "1", "Semester": "2", "Round": "2B", "Bidders": "1", "StudentAcctType": "Returning Students and New Students [P]", "Group": "Seminar-Style Module Class 1"}, {"AcadYear": "2010/2011", "Quota": "9", "Faculty": "Arts & Social Sciences", "HighestBid": "10", "LowestSuccessfulBid": "1", "LowestBid": "10", "Semester": "2", "Round": "2C", "Bidders": "1", "StudentAcctType": "NUS Students [P]", "Group": "Seminar-Style Module Class 1"}, {"AcadYear": "2010/2011", "Quota": "8", "Faculty": "Arts & Social Sciences", "HighestBid": "494", "LowestSuccessfulBid": "1", "LowestBid": "50", "Semester": "2", "Round": "3A", "Bidders": "2", "StudentAcctType": "NUS Students [P]", "Group": "Seminar-Style Module Class 1"}, {"AcadYear": "2010/2011", "Quota": "6", "Faculty": "Arts & Social Sciences", "HighestBid": "2548", "LowestSuccessfulBid": "1", "LowestBid": "10", "Semester": "2", "Round": "3B", "Bidders": "3", "StudentAcctType": "NUS Students [P]", "Group": "Seminar-Style Module Class 1"}, {"AcadYear": "2011/2012", "Quota": "6", "Faculty": "Arts & Social Sciences", "HighestBid": "2500", "LowestSuccessfulBid": "1", "LowestBid": "1", "Semester": "2", "Round": "1A", "Bidders": "5", "StudentAcctType": "Returning Students [P]", "Group": "Seminar-Style Module Class 1"}, {"AcadYear": "2011/2012", "Quota": "1", "Faculty": "Arts & Social Sciences", "HighestBid": "0", "LowestSuccessfulBid": "0", "LowestBid": "0", "Semester": "2", "Round": "1B", "Bidders": "0", "StudentAcctType": "Returning Students [P]", "Group": "Seminar-Style Module Class 1"}, {"AcadYear": "2011/2012", "Quota": "2", "Faculty": "Arts & Social Sciences", "HighestBid": "0", "LowestSuccessfulBid": "0", "LowestBid": "0", "Semester": "2", "Round": "2A", "Bidders": "0", "StudentAcctType": "Returning Students and New Students [P]", "Group": "Seminar-Style Module Class 1"}, {"AcadYear": "2011/2012", "Quota": "3", "Faculty": "Arts & Social Sciences", "HighestBid": "586", "LowestSuccessfulBid": "1", "LowestBid": "586", "Semester": "2", "Round": "2B", "Bidders": "1", "StudentAcctType": "Returning Students and New Students [P]", "Group": "Seminar-Style Module Class 1"}, {"AcadYear": "2011/2012", "Quota": "11", "Faculty": "Arts & Social Sciences", "HighestBid": "0", "LowestSuccessfulBid": "0", "LowestBid": "0", "Semester": "2", "Round": "3A", "Bidders": "0", "StudentAcctType": "NUS Students [P]", "Group": "Seminar-Style Module Class 1"}, {"AcadYear": "2011/2012", "Quota": "12", "Faculty": "Arts & Social Sciences", "HighestBid": "0", "LowestSuccessfulBid": "0", "LowestBid": "0", "Semester": "2", "Round": "3B", "Bidders": "0", "StudentAcctType": "NUS Students [P]", "Group": "Seminar-Style Module Class 1"}, {"AcadYear": "2012/2013", "Quota": "24", "Faculty": "Arts & Social Sciences", "HighestBid": "2900", "LowestSuccessfulBid": "140", "LowestBid": "1", "Semester": "2", "Round": "1A", "Bidders": "30", "StudentAcctType": "Returning Students [P]", "Group": "Seminar-Style Module Class 1"}, {"AcadYear": "2012/2013", "Quota": "1", "Faculty": "Arts & Social Sciences", "HighestBid": "1434", "LowestSuccessfulBid": "1434", "LowestBid": "625", "Semester": "2", "Round": "2B", "Bidders": "3", "StudentAcctType": "Returning Students and New Students [P]", "Group": "Seminar-Style Module Class 1"}, {"AcadYear": "2012/2013", "Quota": "2", "Faculty": "Arts & Social Sciences", "HighestBid": "965", "LowestSuccessfulBid": "696", "LowestBid": "1", "Semester": "2", "Round": "3A", "Bidders": "5", "StudentAcctType": "NUS Students [P]", "Group": "Seminar-Style Module Class 1"}, {"AcadYear": "2013/2014", "Quota": "17", "Faculty": "Arts & Social Sciences", "HighestBid": "345", "LowestSuccessfulBid": "1", "LowestBid": "342", "Semester": "1", "Round": "1A", "Bidders": "2", "StudentAcctType": "Returning Students [P]", "Group": "Seminar-Style Module Class 1"}, {"AcadYear": "2013/2014", "Quota": "15", "Faculty": "Arts & Social Sciences", "HighestBid": "0", "LowestSuccessfulBid": "0", "LowestBid": "0", "Semester": "1", "Round": "1B", "Bidders": "0", "StudentAcctType": "Returning Students [P]", "Group": "Seminar-Style Module Class 1"}, {"AcadYear": "2013/2014", "Quota": "15", "Faculty": "Arts & Social Sciences", "HighestBid": "11", "LowestSuccessfulBid": "1", "LowestBid": "11", "Semester": "1", "Round": "1C", "Bidders": "1", "StudentAcctType": "Returning Students [P]", "Group": "Seminar-Style Module Class 1"}, {"AcadYear": "2013/2014", "Quota": "14", "Faculty": "Arts & Social Sciences", "HighestBid": "500", "LowestSuccessfulBid": "1", "LowestBid": "500", "Semester": "1", "Round": "2A", "Bidders": "1", "StudentAcctType": "Returning Students [P]", "Group": "Seminar-Style Module Class 1"}, {"AcadYear": "2013/2014", "Quota": "13", "Faculty": "Arts & Social Sciences", "HighestBid": "0", "LowestSuccessfulBid": "0", "LowestBid": "0", "Semester": "1", "Round": "2B", "Bidders": "0", "StudentAcctType": "Returning Students [P]", "Group": "Seminar-Style Module Class 1"}, {"AcadYear": "2013/2014", "Quota": "13", "Faculty": "Arts & Social Sciences", "HighestBid": "0", "LowestSuccessfulBid": "0", "LowestBid": "0", "Semester": "1", "Round": "3A", "Bidders": "0", "StudentAcctType": "NUS Students [P]", "Group": "Seminar-Style Module Class 1"}, {"AcadYear": "2013/2014", "Quota": "14", "Faculty": "Arts & Social Sciences", "HighestBid": "600", "LowestSuccessfulBid": "1", "LowestBid": "600", "Semester": "1", "Round": "3B", "Bidders": "1", "StudentAcctType": "NUS Students [P]", "Group": "Seminar-Style Module Class 1"}, {"AcadYear": "2014/2015", "Quota": "17", "Faculty": "Arts & Social Sciences", "HighestBid": "501", "LowestSuccessfulBid": "1", "LowestBid": "1", "Semester": "1", "Round": "1A", "Bidders": "2", "StudentAcctType": "Returning Students [P]", "Group": "Seminar-Style Module Class 1"}, {"AcadYear": "2014/2015", "Quota": "15", "Faculty": "Arts & Social Sciences", "HighestBid": "0", "LowestSuccessfulBid": "0", "LowestBid": "0", "Semester": "1", "Round": "1B", "Bidders": "0", "StudentAcctType": "Returning Students [P]", "Group": "Seminar-Style Module Class 1"}, {"AcadYear": "2014/2015", "Quota": "15", "Faculty": "Arts & Social Sciences", "HighestBid": "1", "LowestSuccessfulBid": "1", "LowestBid": "1", "Semester": "1", "Round": "1C", "Bidders": "4", "StudentAcctType": "Returning Students [P]", "Group": "Seminar-Style Module Class 1"}, {"AcadYear": "2014/2015", "Quota": "11", "Faculty": "Arts & Social Sciences", "HighestBid": "1", "LowestSuccessfulBid": "1", "LowestBid": "1", "Semester": "1", "Round": "2A", "Bidders": "1", "StudentAcctType": "Returning Students [P]", "Group": "Seminar-Style Module Class 1"}, {"AcadYear": "2014/2015", "Quota": "11", "Faculty": "Arts & Social Sciences", "HighestBid": "1", "LowestSuccessfulBid": "1", "LowestBid": "1", "Semester": "1", "Round": "2B", "Bidders": "1", "StudentAcctType": "Returning Students [P]", "Group": "Seminar-Style Module Class 1"}, {"AcadYear": "2014/2015", "Quota": "10", "Faculty": "Arts & Social Sciences", "HighestBid": "0", "LowestSuccessfulBid": "0", "LowestBid": "0", "Semester": "1", "Round": "3A", "Bidders": "0", "StudentAcctType": "NUS Students [P]", "Group": "Seminar-Style Module Class 1"}, {"AcadYear": "2014/2015", "Quota": "10", "Faculty": "Arts & Social Sciences", "HighestBid": "0", "LowestSuccessfulBid": "0", "LowestBid": "0", "Semester": "1", "Round": "3B", "Bidders": "0", "StudentAcctType": "NUS Students [P]", "Group": "Seminar-Style Module Class 1"}, {"AcadYear": "2015/2016", "Quota": "45", "Faculty": "Arts & Social Sciences", "HighestBid": "2642", "LowestSuccessfulBid": "1", "LowestBid": "1", "Semester": "1", "Round": "1A", "Bidders": "18", "StudentAcctType": "Returning Students [P]", "Group": "Seminar-Style Module Class 1"}, {"AcadYear": "2015/2016", "Quota": "27", "Faculty": "Arts & Social Sciences", "HighestBid": "0", "LowestSuccessfulBid": "0", "LowestBid": "0", "Semester": "1", "Round": "1B", "Bidders": "0", "StudentAcctType": "Returning Students [P]", "Group": "Seminar-Style Module Class 1"}, {"AcadYear": "2015/2016", "Quota": "27", "Faculty": "Arts & Social Sciences", "HighestBid": "500", "LowestSuccessfulBid": "1", "LowestBid": "55", "Semester": "1", "Round": "1C", "Bidders": "3", "StudentAcctType": "Returning Students [P]", "Group": "Seminar-Style Module Class 1"}, {"AcadYear": "2015/2016", "Quota": "25", "Faculty": "Arts & Social Sciences", "HighestBid": "0", "LowestSuccessfulBid": "0", "LowestBid": "0", "Semester": "1", "Round": "2A", "Bidders": "0", "StudentAcctType": "Returning Students [P]", "Group": "Seminar-Style Module Class 1"}, {"AcadYear": "2015/2016", "Quota": "25", "Faculty": "Arts & Social Sciences", "HighestBid": "0", "LowestSuccessfulBid": "0", "LowestBid": "0", "Semester": "1", "Round": "2B", "Bidders": "0", "StudentAcctType": "Returning Students [P]", "Group": "Seminar-Style Module Class 1"}, {"AcadYear": "2015/2016", "Quota": "25", "Faculty": "Arts & Social Sciences", "HighestBid": "533", "LowestSuccessfulBid": "1", "LowestBid": "10", "Semester": "1", "Round": "3A", "Bidders": "2", "StudentAcctType": "NUS Students [P]", "Group": "Seminar-Style Module Class 1"}, {"AcadYear": "2015/2016", "Quota": "23", "Faculty": "Arts & Social Sciences", "HighestBid": "0", "LowestSuccessfulBid": "0", "LowestBid": "0", "Semester": "1", "Round": "3B", "Bidders": "0", "StudentAcctType": "NUS Students [P]", "Group": "Seminar-Style Module Class 1"}, {"AcadYear": "2016/2017", "Quota": "40", "Faculty": "Arts & Social Sciences", "HighestBid": "3356", "LowestSuccessfulBid": "1", "LowestBid": "1", "Semester": "1", "Round": "1A", "Bidders": "34", "StudentAcctType": "Returning Students [P]", "Group": "Seminar-Style Module Class 1"}, {"AcadYear": "2016/2017", "Quota": "6", "Faculty": "Arts & Social Sciences", "HighestBid": "1", "LowestSuccessfulBid": "1", "LowestBid": "1", "Semester": "1", "Round": "1B", "Bidders": "2", "StudentAcctType": "Returning Students [P]", "Group": "Seminar-Style Module Class 1"}, {"AcadYear": "2016/2017", "Quota": "4", "Faculty": "Arts & Social Sciences", "HighestBid": "1972", "LowestSuccessfulBid": "1201", "LowestBid": "500", "Semester": "1", "Round": "1C", "Bidders": "7", "StudentAcctType": "Returning Students [P]", "Group": "Seminar-Style Module Class 1"}, {"AcadYear": "2016/2017", "Quota": "1", "Faculty": "Arts & Social Sciences", "HighestBid": "2204", "LowestSuccessfulBid": "2204", "LowestBid": "1568", "Semester": "1", "Round": "2A", "Bidders": "2", "StudentAcctType": "Returning Students [P]", "Group": "Seminar-Style Module Class 1"}, {"AcadYear": "2016/2017", "Quota": "1", "Faculty": "Arts & Social Sciences", "HighestBid": "2208", "LowestSuccessfulBid": "2208", "LowestBid": "147", "Semester": "1", "Round": "2B", "Bidders": "3", "StudentAcctType": "Returning Students [P]", "Group": "Seminar-Style Module Class 1"}, {"AcadYear": "2016/2017", "Quota": "1", "Faculty": "Arts & Social Sciences", "HighestBid": "2337", "LowestSuccessfulBid": "2337", "LowestBid": "658", "Semester": "1", "Round": "3B", "Bidders": "4", "StudentAcctType": "NUS Students [P]", "Group": "Seminar-Style Module Class 1"}], "ModmavenTree": {"name": "EC4303", "children": []}, "ModuleCredit": "5"}