{"ModuleCode": "GS6889A", "LockedModules": [], "History": [{"Semester": 2}], "ModuleTitle": "Academic Professional Skills II", "Prerequisite": "The skills capsules are timed.", "Workload": "2-0-0-8-2", "Preclusion": "NIL", "AcadYear": "2017/2018", "Corequisite": "NIL", "ModuleDescription": "The Professional Skills series enables students better to approach, present, and otherwise communicate their research. Students are helped to understand what graduate level research involves, how to gauge their own progress and set appropriate goals, to read critically, listen effectively, write-up and present their research to different audiences - peers, lab meetings, conferences, grant bodies, journals, and thesis examiners. Each skills capsule will be timed relevantly to accord with the different stages of the PhD degree.", "Department": "NUS Grad Sch For Integrative Sci & Engg", "ModmavenTree": {"name": "GS6889A", "children": []}, "ModuleCredit": "2"}