{"ModuleCode": "LL6319V", "LockedModules": [], "History": [{"Semester": 2}], "ModuleTitle": "Current Problems in International Law", "Prerequisite": "NUS Compulsory Core Law Curriculum or equivalent.", "Workload": "0-3-0-0-7", "Preclusion": "LL4319/LL5319/LL6319 Current Problems in International Law", "AcadYear": "2017/2018", "Corequisite": "Public International Law is recommended.", "ModuleDescription": "This course examines current problems in international law relating, for instance, to the use of force, human rights, international environmental law and foreign investment law.", "Department": "Law", "ParsedPreclusion": {"or": ["LL4319", "LL5319"]}, "ModmavenTree": {"name": "LL6319V", "children": []}, "ModuleCredit": "5"}