{"ModuleCode": "MUA3264", "Types": ["Module"], "History": [{"Semester": 2}, {"Semester": 1}], "Workload": "1-0-0-5-4", "ModuleTitle": "PD Independent Project", "Prerequisite": "Pre-requisite of 5 MCs of Professional Development modules", "LockedModules": [], "Preclusion": "NIL", "AcadYear": "2017/2018", "Corequisite": "", "ModuleDescription": "Building on previously completed professional development modules, students will design, develop and implement a music-related project in an external environment. Students will also incorporate strategies and materials for promoting their careers using traditional and new media.", "Department": "Yong Siew Toh Conservatory Of Music", "ModmavenTree": {"name": "MUA3264", "children": []}, "ModuleCredit": "4"}