{"ModuleCode": "NUR2116", "Types": ["Module"], "History": [{"ExamDate": "2017-11-27T09:00+0800", "LecturePeriods": ["Wednesday Afternoon"], "Timetable": [{"LessonType": "Laboratory", "WeekText": "Every Week", "DayText": "Thursday", "Venue": "DV", "ClassNo": "1", "EndTime": "1200", "StartTime": "1000"}, {"LessonType": "Laboratory", "WeekText": "Every Week", "DayText": "Thursday", "Venue": "DV", "ClassNo": "2", "EndTime": "1200", "StartTime": "1000"}, {"LessonType": "Laboratory", "WeekText": "Every Week", "DayText": "Thursday", "Venue": "DV", "ClassNo": "3", "EndTime": "1600", "StartTime": "1400"}, {"LessonType": "Laboratory", "WeekText": "Every Week", "DayText": "Thursday", "Venue": "DV", "ClassNo": "4", "EndTime": "1600", "StartTime": "1400"}, {"LessonType": "Laboratory", "WeekText": "Every Week", "DayText": "Friday", "Venue": "DV", "ClassNo": "5", "EndTime": "1200", "StartTime": "1000"}, {"LessonType": "Laboratory", "WeekText": "Every Week", "DayText": "Friday", "Venue": "DV", "ClassNo": "6", "EndTime": "1200", "StartTime": "1000"}, {"LessonType": "Laboratory", "WeekText": "Every Week", "DayText": "Friday", "Venue": "DV", "ClassNo": "7", "EndTime": "1400", "StartTime": "1200"}, {"LessonType": "Laboratory", "WeekText": "Every Week", "DayText": "Friday", "Venue": "DV", "ClassNo": "8", "EndTime": "1400", "StartTime": "1200"}, {"LessonType": "Lecture", "WeekText": "Every Week", "DayText": "Wednesday", "Venue": "DV", "ClassNo": "1", "EndTime": "1300", "StartTime": "1200"}, {"LessonType": "Tutorial", "WeekText": "Every Week", "DayText": "Thursday", "Venue": "DV", "ClassNo": "1", "EndTime": "1000", "StartTime": "0800"}, {"LessonType": "Tutorial", "WeekText": "Every Week", "DayText": "Thursday", "Venue": "DV", "ClassNo": "2", "EndTime": "1000", "StartTime": "0800"}, {"LessonType": "Tutorial", "WeekText": "Every Week", "DayText": "Thursday", "Venue": "DV", "ClassNo": "3", "EndTime": "1200", "StartTime": "1000"}, {"LessonType": "Tutorial", "WeekText": "Every Week", "DayText": "Thursday", "Venue": "DV", "ClassNo": "4", "EndTime": "1200", "StartTime": "1000"}, {"LessonType": "Tutorial", "WeekText": "Every Week", "DayText": "Friday", "Venue": "DV", "ClassNo": "5", "EndTime": "1000", "StartTime": "0800"}, {"LessonType": "Tutorial", "WeekText": "Every Week", "DayText": "Friday", "Venue": "DV", "ClassNo": "6", "EndTime": "1000", "StartTime": "0800"}, {"LessonType": "Tutorial", "WeekText": "Every Week", "DayText": "Friday", "Venue": "DV", "ClassNo": "7", "EndTime": "1200", "StartTime": "1000"}, {"LessonType": "Tutorial", "WeekText": "Every Week", "DayText": "Friday", "Venue": "DV", "ClassNo": "8", "EndTime": "1200", "StartTime": "1000"}], "Semester": 1, "TutorialPeriods": ["Thursday Morning", "Thursday Afternoon", "Friday Morning", "Friday Afternoon"]}], "Workload": "1-2-2-2-3", "ModuleTitle": "Medical-Surgical Nursing II", "Prerequisite": "NUR1108A Nursing Practice Experience 1.2 to replace existing pre-requisite.", "LockedModules": [], "ParsedPrerequisite": "NUR1108A", "AcadYear": "2017/2018", "Corequisite": "NUR2118 Pathophysiology & Pharmacology for Nurses II, NUR2106A Nursing Practice Experience 2.1", "ModuleDescription": "This module will promote and develop knowledge, skills and attitudes necessary for the provision of nursing care and management for patients with alteration in gastrointestinal, musculoskeletal, renal and urinary, and immunological function. The module also includes management of patients in pain and patients in the operating room.", "Department": "Nursing/Alice Lee Ctr For Nursing Stud", "ModmavenTree": {"name": "NUR2116", "children": {"name": "NUR1108A", "children": []}}, "ModuleCredit": "4"}