{"ModuleCode": "PC3288", "Types": ["Module"], "History": [{"Semester": 4}, {"Semester": 3}, {"Semester": 2}, {"Semester": 1}], "Workload": "To be designed on consultation", "ModuleTitle": "Advanced UROPS in Physics I", "Prerequisite": "Departmental Approval", "LockedModules": [], "AcadYear": "2017/2018", "ModuleDescription": "Please note also that only 4MCs can be accredited towards major requirements in case that a student undertakes 8MCs for both PC3288 and PC3289.", "Department": "Physics", "ModmavenTree": {"name": "PC3288", "children": []}, "ModuleCredit": "4"}