{"ModuleCode": "PR3136", "LockedModules": ["PR4138"], "History": [{"ExamDate": "2018-05-09T09:00+0800", "Semester": 2}], "ModuleTitle": "Pharmacotherapeutics IV", "Prerequisite": "PR2135", "Workload": "4-0-0-2-4", "ParsedPrerequisite": "PR2135", "AcadYear": "2017/2018", "ModuleDescription": "This is a team-taught module that aims to prepare pharmacy students in the management of noncommunicable diseases through the integration of pharmacology and pharmacotherapeutics. Major topics include psychiatry, neurology and oncology.", "Department": "Pharmacy", "ModmavenTree": {"name": "PR3136", "children": {"name": "PR2135", "children": []}}, "ModuleCredit": "4"}