{"ModuleCode": "SE3218", "LockedModules": [], "History": [{"ExamDate": "2018-05-02T09:00+0800", "Semester": 2}], "ModuleTitle": "Industrialising Singapore and SE Asia", "Prerequisite": "Nil", "Workload": "2-1-0-4-3", "Preclusion": "SE2215", "AcadYear": "2017/2018", "ModuleDescription": "Industrialisation involves the promotion and development of the industrial sector. Why have some countries industrialised faster than others? In particular, the manufacturing industries in some countries have remained backward and depended heavily on the use of labour while in other countries, they have become more advanced and relied more on the use of capital. This module discusses the theory and concepts that relate to industrialisation. It also investigates the industrial experiences of other countries and the lessons from them. Focus will be on Singapore, and how it compares with other SE Asian countries.", "Department": "Southeast Asian Studies", "ParsedPreclusion": "SE2215", "CorsBiddingStats": [{"AcadYear": "2011/2012", "Quota": "14", "Faculty": "Arts & Social Sciences", "HighestBid": "3", "LowestSuccessfulBid": "1", "LowestBid": "2", "Semester": "2", "Round": "1A", "Bidders": "2", "StudentAcctType": "Returning Students [P]", "Group": "Lecture 1"}, {"AcadYear": "2011/2012", "Quota": "5", "Faculty": "Arts & Social Sciences", "HighestBid": "0", "LowestSuccessfulBid": "0", "LowestBid": "0", "Semester": "2", "Round": "1A", "Bidders": "0", "StudentAcctType": "New Students [P]", "Group": "Lecture 1"}, {"AcadYear": "2011/2012", "Quota": "12", "Faculty": "Arts & Social Sciences", "HighestBid": "0", "LowestSuccessfulBid": "0", "LowestBid": "0", "Semester": "2", "Round": "1B", "Bidders": "0", "StudentAcctType": "Returning Students [P]", "Group": "Lecture 1"}, {"AcadYear": "2011/2012", "Quota": "5", "Faculty": "Arts & Social Sciences", "HighestBid": "0", "LowestSuccessfulBid": "0", "LowestBid": "0", "Semester": "2", "Round": "1B", "Bidders": "0", "StudentAcctType": "New Students [P]", "Group": "Lecture 1"}, {"AcadYear": "2011/2012", "Quota": "17", "Faculty": "Arts & Social Sciences", "HighestBid": "0", "LowestSuccessfulBid": "0", "LowestBid": "0", "Semester": "2", "Round": "2A", "Bidders": "0", "StudentAcctType": "Returning Students and New Students [P]", "Group": "Lecture 1"}, {"AcadYear": "2011/2012", "Quota": "10", "Faculty": "Arts & Social Sciences", "HighestBid": "0", "LowestSuccessfulBid": "0", "LowestBid": "0", "Semester": "2", "Round": "2A", "Bidders": "0", "StudentAcctType": "Reserved for [G] in later round", "Group": "Lecture 1"}, {"AcadYear": "2011/2012", "Quota": "18", "Faculty": "Arts & Social Sciences", "HighestBid": "0", "LowestSuccessfulBid": "0", "LowestBid": "0", "Semester": "2", "Round": "2B", "Bidders": "0", "StudentAcctType": "Returning Students and New Students [P]", "Group": "Lecture 1"}, {"AcadYear": "2011/2012", "Quota": "10", "Faculty": "Arts & Social Sciences", "HighestBid": "0", "LowestSuccessfulBid": "0", "LowestBid": "0", "Semester": "2", "Round": "2B", "Bidders": "0", "StudentAcctType": "NUS Students [G]", "Group": "Lecture 1"}, {"AcadYear": "2011/2012", "Quota": "28", "Faculty": "Arts & Social Sciences", "HighestBid": "0", "LowestSuccessfulBid": "0", "LowestBid": "0", "Semester": "2", "Round": "3A", "Bidders": "0", "StudentAcctType": "NUS Students [P, G]", "Group": "Lecture 1"}, {"AcadYear": "2011/2012", "Quota": "29", "Faculty": "Arts & Social Sciences", "HighestBid": "0", "LowestSuccessfulBid": "0", "LowestBid": "0", "Semester": "2", "Round": "3B", "Bidders": "0", "StudentAcctType": "NUS Students [P, G]", "Group": "Lecture 1"}, {"AcadYear": "2012/2013", "Quota": "11", "Faculty": "Arts & Social Sciences", "HighestBid": "1500", "LowestSuccessfulBid": "1", "LowestBid": "101", "Semester": "2", "Round": "1A", "Bidders": "2", "StudentAcctType": "Returning Students [P]", "Group": "Lecture 1"}, {"AcadYear": "2012/2013", "Quota": "15", "Faculty": "Arts & Social Sciences", "HighestBid": "0", "LowestSuccessfulBid": "0", "LowestBid": "0", "Semester": "2", "Round": "1A", "Bidders": "0", "StudentAcctType": "New Students [P]", "Group": "Lecture 1"}, {"AcadYear": "2012/2013", "Quota": "9", "Faculty": "Arts & Social Sciences", "HighestBid": "0", "LowestSuccessfulBid": "0", "LowestBid": "0", "Semester": "2", "Round": "1B", "Bidders": "0", "StudentAcctType": "Returning Students [P]", "Group": "Lecture 1"}, {"AcadYear": "2012/2013", "Quota": "15", "Faculty": "Arts & Social Sciences", "HighestBid": "0", "LowestSuccessfulBid": "0", "LowestBid": "0", "Semester": "2", "Round": "1B", "Bidders": "0", "StudentAcctType": "New Students [P]", "Group": "Lecture 1"}, {"AcadYear": "2012/2013", "Quota": "24", "Faculty": "Arts & Social Sciences", "HighestBid": "0", "LowestSuccessfulBid": "0", "LowestBid": "0", "Semester": "2", "Round": "2A", "Bidders": "0", "StudentAcctType": "Returning Students and New Students [P]", "Group": "Lecture 1"}, {"AcadYear": "2012/2013", "Quota": "5", "Faculty": "Arts & Social Sciences", "HighestBid": "0", "LowestSuccessfulBid": "0", "LowestBid": "0", "Semester": "2", "Round": "2A", "Bidders": "0", "StudentAcctType": "Reserved for [G] in later round", "Group": "Lecture 1"}, {"AcadYear": "2012/2013", "Quota": "24", "Faculty": "Arts & Social Sciences", "HighestBid": "50", "LowestSuccessfulBid": "1", "LowestBid": "28", "Semester": "2", "Round": "2B", "Bidders": "2", "StudentAcctType": "Returning Students and New Students [P]", "Group": "Lecture 1"}, {"AcadYear": "2012/2013", "Quota": "5", "Faculty": "Arts & Social Sciences", "HighestBid": "0", "LowestSuccessfulBid": "0", "LowestBid": "0", "Semester": "2", "Round": "2B", "Bidders": "0", "StudentAcctType": "NUS Students [G]", "Group": "Lecture 1"}, {"AcadYear": "2012/2013", "Quota": "27", "Faculty": "Arts & Social Sciences", "HighestBid": "1", "LowestSuccessfulBid": "1", "LowestBid": "1", "Semester": "2", "Round": "3A", "Bidders": "1", "StudentAcctType": "NUS Students [P, G]", "Group": "Lecture 1"}, {"AcadYear": "2012/2013", "Quota": "26", "Faculty": "Arts & Social Sciences", "HighestBid": "0", "LowestSuccessfulBid": "0", "LowestBid": "0", "Semester": "2", "Round": "3B", "Bidders": "0", "StudentAcctType": "NUS Students [P, G]", "Group": "Lecture 1"}, {"AcadYear": "2013/2014", "Quota": "13", "Faculty": "Arts & Social Sciences", "HighestBid": "0", "LowestSuccessfulBid": "0", "LowestBid": "0", "Semester": "2", "Round": "1A", "Bidders": "0", "StudentAcctType": "Returning Students [P]", "Group": "Lecture 1"}, {"AcadYear": "2013/2014", "Quota": "15", "Faculty": "Arts & Social Sciences", "HighestBid": "0", "LowestSuccessfulBid": "0", "LowestBid": "0", "Semester": "2", "Round": "1A", "Bidders": "0", "StudentAcctType": "New Students [P]", "Group": "Lecture 1"}, {"AcadYear": "2013/2014", "Quota": "13", "Faculty": "Arts & Social Sciences", "HighestBid": "0", "LowestSuccessfulBid": "0", "LowestBid": "0", "Semester": "2", "Round": "1B", "Bidders": "0", "StudentAcctType": "Returning Students [P]", "Group": "Lecture 1"}, {"AcadYear": "2013/2014", "Quota": "15", "Faculty": "Arts & Social Sciences", "HighestBid": "0", "LowestSuccessfulBid": "0", "LowestBid": "0", "Semester": "2", "Round": "1B", "Bidders": "0", "StudentAcctType": "New Students [P]", "Group": "Lecture 1"}, {"AcadYear": "2013/2014", "Quota": "28", "Faculty": "Arts & Social Sciences", "HighestBid": "0", "LowestSuccessfulBid": "0", "LowestBid": "0", "Semester": "2", "Round": "2A", "Bidders": "0", "StudentAcctType": "Returning Students and New Students [P]", "Group": "Lecture 1"}, {"AcadYear": "2013/2014", "Quota": "5", "Faculty": "Arts & Social Sciences", "HighestBid": "0", "LowestSuccessfulBid": "0", "LowestBid": "0", "Semester": "2", "Round": "2A", "Bidders": "0", "StudentAcctType": "Reserved for [G] in later round", "Group": "Lecture 1"}, {"AcadYear": "2013/2014", "Quota": "28", "Faculty": "Arts & Social Sciences", "HighestBid": "1644", "LowestSuccessfulBid": "1", "LowestBid": "1", "Semester": "2", "Round": "2B", "Bidders": "3", "StudentAcctType": "Returning Students and New Students [P]", "Group": "Lecture 1"}, {"AcadYear": "2013/2014", "Quota": "5", "Faculty": "Arts & Social Sciences", "HighestBid": "0", "LowestSuccessfulBid": "0", "LowestBid": "0", "Semester": "2", "Round": "2B", "Bidders": "0", "StudentAcctType": "NUS Students [G]", "Group": "Lecture 1"}, {"AcadYear": "2013/2014", "Quota": "30", "Faculty": "Arts & Social Sciences", "HighestBid": "0", "LowestSuccessfulBid": "0", "LowestBid": "0", "Semester": "2", "Round": "3A", "Bidders": "0", "StudentAcctType": "NUS Students [P, G]", "Group": "Lecture 1"}, {"AcadYear": "2013/2014", "Quota": "30", "Faculty": "Arts & Social Sciences", "HighestBid": "0", "LowestSuccessfulBid": "0", "LowestBid": "0", "Semester": "2", "Round": "3B", "Bidders": "0", "StudentAcctType": "NUS Students [P, G]", "Group": "Lecture 1"}], "ModmavenTree": {"name": "SE3218", "children": []}, "ModuleCredit": "4"}