{"ModuleCode": "SW4208", "Types": ["Module"], "History": [{"ExamDate": "2018-05-04T14:30+0800", "Semester": 2}, {"ExamDate": "2017-12-01T09:00+0800", "Timetable": [{"LessonType": "Seminar-Style Module Class", "WeekText": "Every Week", "DayText": "Friday", "Venue": "AS6-0212", "ClassNo": "1", "EndTime": "1900", "StartTime": "1600"}], "Semester": 1, "LecturePeriods": ["Friday Afternoon"]}], "Workload": "0-3-0-2-7.5", "ModuleTitle": "Social Gerontology", "Prerequisite": "Cohort 2011 and before: Completed 80MCs, including 28MCs in SW of which (i) student must have passed SW1101E, SW2101, SW2104, SW2105, and SW3103A with a minimum CAP of 3.50 or be on the Honours track. Cohort 2012 onwards: Completed 80MCs, including 28MCs in SW of which (i) student must have passed SW1101E, SW2101, SW2104, SW2105, and SW3103A with a minimum CAP of 3.20 or be on the Honours track.", "LockedModules": [], "Preclusion": "Nil", "AcadYear": "2017/2018", "ModuleDescription": "This module examines the physiological, psychological, socio-cultural contexts of ageing and the attendant implications for individuals, families, and societies. Macro issues such as the impact of longer life expectancy, a greying workforce, and 'feminization of ageing' would be brainstormed in a seminar style of teaching. Social policies, social interventions and the impact of economic and social contexts on the well being of older people would increase the students' awareness and understanding of gerontological issues. Through interactive teaching, the students will learn about the theories of ageing and social policy issues such as income security, health care, housing, and leisure activities.", "Department": "Social Work", "CorsBiddingStats": [{"AcadYear": "2010/2011", "Quota": "31", "Faculty": "Arts & Social Sciences", "HighestBid": "2400", "LowestSuccessfulBid": "1", "LowestBid": "1", "Semester": "2", "Round": "1A", "Bidders": "5", "StudentAcctType": "Returning Students [P]", "Group": "Seminar-Style Module Class 1"}, {"AcadYear": "2010/2011", "Quota": "26", "Faculty": "Arts & Social Sciences", "HighestBid": "0", "LowestSuccessfulBid": "0", "LowestBid": "0", "Semester": "2", "Round": "1B", "Bidders": "0", "StudentAcctType": "Returning Students [P]", "Group": "Seminar-Style Module Class 1"}, {"AcadYear": "2010/2011", "Quota": "26", "Faculty": "Arts & Social Sciences", "HighestBid": "0", "LowestSuccessfulBid": "0", "LowestBid": "0", "Semester": "2", "Round": "2A", "Bidders": "0", "StudentAcctType": "Returning Students and New Students [P]", "Group": "Seminar-Style Module Class 1"}, {"AcadYear": "2010/2011", "Quota": "26", "Faculty": "Arts & Social Sciences", "HighestBid": "0", "LowestSuccessfulBid": "0", "LowestBid": "0", "Semester": "2", "Round": "2B", "Bidders": "0", "StudentAcctType": "Returning Students and New Students [P]", "Group": "Seminar-Style Module Class 1"}, {"AcadYear": "2010/2011", "Quota": "26", "Faculty": "Arts & Social Sciences", "HighestBid": "0", "LowestSuccessfulBid": "0", "LowestBid": "0", "Semester": "2", "Round": "2C", "Bidders": "0", "StudentAcctType": "NUS Students [P]", "Group": "Seminar-Style Module Class 1"}, {"AcadYear": "2010/2011", "Quota": "26", "Faculty": "Arts & Social Sciences", "HighestBid": "350", "LowestSuccessfulBid": "1", "LowestBid": "1", "Semester": "2", "Round": "3A", "Bidders": "2", "StudentAcctType": "NUS Students [P]", "Group": "Seminar-Style Module Class 1"}, {"AcadYear": "2010/2011", "Quota": "24", "Faculty": "Arts & Social Sciences", "HighestBid": "0", "LowestSuccessfulBid": "0", "LowestBid": "0", "Semester": "2", "Round": "3B", "Bidders": "0", "StudentAcctType": "NUS Students [P]", "Group": "Seminar-Style Module Class 1"}, {"AcadYear": "2012/2013", "Quota": "25", "Faculty": "Arts & Social Sciences", "HighestBid": "649", "LowestSuccessfulBid": "1", "LowestBid": "1", "Semester": "2", "Round": "1A", "Bidders": "7", "StudentAcctType": "Returning Students [P]", "Group": "Seminar-Style Module Class 1"}, {"AcadYear": "2012/2013", "Quota": "18", "Faculty": "Arts & Social Sciences", "HighestBid": "0", "LowestSuccessfulBid": "0", "LowestBid": "0", "Semester": "2", "Round": "1B", "Bidders": "0", "StudentAcctType": "Returning Students [P]", "Group": "Seminar-Style Module Class 1"}, {"AcadYear": "2012/2013", "Quota": "18", "Faculty": "Arts & Social Sciences", "HighestBid": "0", "LowestSuccessfulBid": "0", "LowestBid": "0", "Semester": "2", "Round": "2A", "Bidders": "0", "StudentAcctType": "Returning Students and New Students [P]", "Group": "Seminar-Style Module Class 1"}, {"AcadYear": "2012/2013", "Quota": "18", "Faculty": "Arts & Social Sciences", "HighestBid": "883", "LowestSuccessfulBid": "1", "LowestBid": "1", "Semester": "2", "Round": "2B", "Bidders": "8", "StudentAcctType": "Returning Students and New Students [P]", "Group": "Seminar-Style Module Class 1"}, {"AcadYear": "2012/2013", "Quota": "10", "Faculty": "Arts & Social Sciences", "HighestBid": "0", "LowestSuccessfulBid": "0", "LowestBid": "0", "Semester": "2", "Round": "3A", "Bidders": "0", "StudentAcctType": "NUS Students [P]", "Group": "Seminar-Style Module Class 1"}, {"AcadYear": "2012/2013", "Quota": "10", "Faculty": "Arts & Social Sciences", "HighestBid": "0", "LowestSuccessfulBid": "0", "LowestBid": "0", "Semester": "2", "Round": "3B", "Bidders": "0", "StudentAcctType": "NUS Students [P]", "Group": "Seminar-Style Module Class 1"}, {"AcadYear": "2014/2015", "Quota": "14", "Faculty": "Arts & Social Sciences", "HighestBid": "0", "LowestSuccessfulBid": "0", "LowestBid": "0", "Semester": "1", "Round": "1A", "Bidders": "0", "StudentAcctType": "Returning Students [P]", "Group": "Seminar-Style Module Class 1"}, {"AcadYear": "2014/2015", "Quota": "14", "Faculty": "Arts & Social Sciences", "HighestBid": "0", "LowestSuccessfulBid": "0", "LowestBid": "0", "Semester": "1", "Round": "1B", "Bidders": "0", "StudentAcctType": "Returning Students [P]", "Group": "Seminar-Style Module Class 1"}, {"AcadYear": "2014/2015", "Quota": "14", "Faculty": "Arts & Social Sciences", "HighestBid": "0", "LowestSuccessfulBid": "0", "LowestBid": "0", "Semester": "1", "Round": "1C", "Bidders": "0", "StudentAcctType": "Returning Students [P]", "Group": "Seminar-Style Module Class 1"}, {"AcadYear": "2014/2015", "Quota": "14", "Faculty": "Arts & Social Sciences", "HighestBid": "1", "LowestSuccessfulBid": "1", "LowestBid": "1", "Semester": "1", "Round": "2A", "Bidders": "1", "StudentAcctType": "Returning Students [P]", "Group": "Seminar-Style Module Class 1"}, {"AcadYear": "2014/2015", "Quota": "13", "Faculty": "Arts & Social Sciences", "HighestBid": "20", "LowestSuccessfulBid": "1", "LowestBid": "20", "Semester": "1", "Round": "2B", "Bidders": "1", "StudentAcctType": "Returning Students [P]", "Group": "Seminar-Style Module Class 1"}, {"AcadYear": "2014/2015", "Quota": "12", "Faculty": "Arts & Social Sciences", "HighestBid": "1", "LowestSuccessfulBid": "1", "LowestBid": "1", "Semester": "1", "Round": "3A", "Bidders": "1", "StudentAcctType": "NUS Students [P]", "Group": "Seminar-Style Module Class 1"}, {"AcadYear": "2014/2015", "Quota": "11", "Faculty": "Arts & Social Sciences", "HighestBid": "0", "LowestSuccessfulBid": "0", "LowestBid": "0", "Semester": "1", "Round": "3B", "Bidders": "0", "StudentAcctType": "NUS Students [P]", "Group": "Seminar-Style Module Class 1"}, {"AcadYear": "2016/2017", "Quota": "50", "Faculty": "Arts & Social Sciences", "HighestBid": "2358", "LowestSuccessfulBid": "1", "LowestBid": "1", "Semester": "1", "Round": "1A", "Bidders": "49", "StudentAcctType": "Returning Students [P]", "Group": "Seminar-Style Module Class 1"}, {"AcadYear": "2016/2017", "Quota": "1", "Faculty": "Arts & Social Sciences", "HighestBid": "1", "LowestSuccessfulBid": "1", "LowestBid": "1", "Semester": "1", "Round": "1B", "Bidders": "1", "StudentAcctType": "Returning Students [P]", "Group": "Seminar-Style Module Class 1"}, {"AcadYear": "2016/2017", "Quota": "1", "Faculty": "Arts & Social Sciences", "HighestBid": "1", "LowestSuccessfulBid": "1", "LowestBid": "1", "Semester": "1", "Round": "1C", "Bidders": "1", "StudentAcctType": "Returning Students [P]", "Group": "Seminar-Style Module Class 1"}, {"AcadYear": "2016/2017", "Quota": "1", "Faculty": "Arts & Social Sciences", "HighestBid": "976", "LowestSuccessfulBid": "1", "LowestBid": "976", "Semester": "1", "Round": "3B", "Bidders": "1", "StudentAcctType": "NUS Students [P]", "Group": "Seminar-Style Module Class 1"}], "ModmavenTree": {"name": "SW4208", "children": []}, "ModuleCredit": "5"}